{"id":"ship_spl_m_trans_container_01_a_macro","class":"ship_m","race":"spl","name":"Boa","basename":"Boa","description":null,"shortvariation":"BV","variation":null,"type":"transporter","radarRange":"40000","docksize":"dock_m","hull":"7400","shield":{"max":0,"rate":0,"delay":0},"speed":{"forward":0,"acceleration":0,"boost":0,"travel":0,"pitch":0,"roll":0,"yaw":0},"armaments":{"weapons":{"extralarge":0,"large":0,"medium":0,"small":0},"turrets":{"extralarge":0,"large":0,"medium":2,"small":0}},"storage":{"unit":null,"missile":20,"people":20,"countermeasure":8,"deployable":100,"capacity":7500,"capacityType":"container"},"mass":"56.286","inertia":{"pitch":"15.581","yaw":"15.581","roll":"12.465"},"drag":{"forward":"8.887","reverse":"35.546","horizontal":"23.845","vertical":"23.845","pitch":"16.572","yaw":"16.572","roll":"16.572"},"thrusters":{"size":"medium"},"shipstorage":{"dock_m":0,"dock_s":0},"turrets":[{"quantity":1,"size":"medium"},{"quantity":1,"size":"medium"}],"weapons":[],"shields":{"size":"medium","quantity":1},"engines":{"size":"medium","quantity":2},"specialExit":true,"price":{"min":"317679","average":"373740","max":"429801"},"production":{"time":"23","amount":"1","method":"default","name":"{20206,101}","primary":{"ware":[{"ware":"energycells","amount":"126"},{"ware":"hullparts","amount":"348"}]}},"manufacturer":"freesplit"}