{"id":"ship_tel_s_miner_solid_01_a_macro","class":"ship_s","race":"tel","name":"Magpie (Mineral)","basename":"undefined","description":"undefined","shortvariation":"BV","variation":"Base Variation","type":"miner","radarRange":"40000","docksize":"dock_s","hull":1300,"shield":{"max":0,"rate":0,"delay":0},"speed":{"forward":0,"acceleration":0,"boost":0,"travel":0,"pitch":0,"roll":0,"yaw":0},"armaments":{"weapons":{"extralarge":0,"large":0,"medium":0,"small":1},"turrets":{"extralarge":0,"large":0,"medium":0,"small":0}},"storage":{"unit":null,"missile":10,"people":3,"countermeasure":4,"deployable":50,"capacity":3500,"capacityType":"solid"},"mass":10.259,"inertia":{"pitch":4.771,"yaw":4.771,"roll":3.817},"drag":{"forward":4.409,"reverse":22.905,"horizontal":5.323,"vertical":5.323,"pitch":6.708,"yaw":6.708,"roll":6.708},"thrusters":{"size":"small"},"shipstorage":{"dock_m":0,"dock_s":0},"turrets":[],"weapons":[{"quantity":1,"size":"small","standard":true,"missile":true}],"shields":{"size":"small","quantity":2},"engines":{"size":"small","quantity":2},"specialExit":false,"price":{"min":"77197","average":"90820","max":"104443"},"production":{"time":"7","amount":"1","method":"default","name":"{20206,101}","primary":{"ware":[{"ware":"energycells","amount":"38"},{"ware":"hullparts","amount":"84"}]}},"manufacturer":"ministry"}